waldcli/__init__.py
waldcli/butler.py
waldcli/prompt.py
waldcli-0.2.3.dist-info/entry_points.txt
waldcli-0.2.3.dist-info/LICENSE
waldcli-0.2.3.dist-info/WHEEL
waldcli-0.2.3.dist-info/METADATA
waldcli-0.2.3.dist-info/RECORD
