Metadata-Version: 2.1
Name: waldcli
Version: 0.2.3
Summary: The waldemar client for web projects (using docker)
Home-page: https://gitlab.com/welance/internal/waldcli
License: MIT
Author: andrea giacobino
Author-email: no.andrea@gmail.com
Requires-Python: >=3.7,<4.0
Classifier: License :: OSI Approved :: MIT License
Classifier: Programming Language :: Python :: 3
Classifier: Programming Language :: Python :: 3.7
Requires-Dist: PyYAML (==3.13)
Requires-Dist: colorama (>=0.4.1,<0.5.0)
Requires-Dist: requests (>=2,<3)
